_re2.cc
re2.py
setup.py
cjworkbench_re2.egg-info/PKG-INFO
cjworkbench_re2.egg-info/SOURCES.txt
cjworkbench_re2.egg-info/dependency_links.txt
cjworkbench_re2.egg-info/requires.txt
cjworkbench_re2.egg-info/top_level.txt