Metadata-Version: 2.1
Name: cjworkbench-re2
Version: 0.0.7a0
Summary: RE2 Python bindings
Home-page: https://github.com/google/re2
Author: The RE2 Authors
Author-email: re2-dev@googlegroups.com
License: UNKNOWN
Platform: UNKNOWN
Classifier: Development Status :: 5 - Production/Stable
Classifier: Intended Audience :: Developers
Classifier: License :: OSI Approved :: BSD License
Classifier: Programming Language :: C++
Classifier: Programming Language :: Python :: 3.6
Requires-Python: ~=3.6
